good_dev/__init__.py
good_dev/config.py
good_dev/py.typed
good_dev/utilities.py
good_dev/cli/__init__.py
good_dev/cli/commands/__init__.py
good_dev/cli/commands/config.py
good_dev/cli/commands/packages.py
good_dev/cli/commands/run.py
good_dev/tools/__init__.py
good_dev/tools/dependency_explorer.py
good_dev/tools/wheelodex/__init__.py
good_dev/tools/wheelodex/_api.py
good_dev-0.1.1.dist-info/METADATA
good_dev-0.1.1.dist-info/WHEEL
good_dev-0.1.1.dist-info/entry_points.txt
good_dev-0.1.1.dist-info/RECORD
