Metadata-Version: 2.4
Name: good-dev
Version: 0.1.1
Summary: Add your description here
Author-email: Chris Goddard <chris@goodkiwi.llc>
Requires-Python: >=3.12.8
Requires-Dist: cashews>=7.4.0
Requires-Dist: diskcache>=5.6.3
Requires-Dist: good-common>=0.2.0
Requires-Dist: httpx>=0.24.0
Requires-Dist: loguru>=0.7.0
Requires-Dist: rich>=13.0.0
Requires-Dist: simple-toml-configurator>=1.3.0
Requires-Dist: tenacity>=8.0.0
Requires-Dist: tqdm>=4.65.0
Requires-Dist: typer>=0.9.0
Provides-Extra: dev
Requires-Dist: pytest-asyncio>=0.21.0; extra == 'dev'
Requires-Dist: pytest>=7.0.0; extra == 'dev'
